[
  {
    "title": "Calacatta Gold Tile",
    "category": "tile",
    "style": "marble-look",
    "image": "/images/tile-calacatta-gold-large.jpg",
    "detailPage": "/material-detail-calacatta-gold-tile.html"
  },
  {
    "title": "Geo Lines Wallpaper",
    "category": "wallpaper",
    "style": "geometric",
    "image": "/images/wallpaper-geo-lines-large.jpg",
    "detailPage": "/material-detail-geo-lines-wallpaper.html"
  },
  {
    "title": "Light Oak Slat Panel",
    "category": "pvc-panel",
    "style": "wood-look",
    "image": "/images/pvc-panel-light-oak.jpg",
    "detailPage": "/material-detail-light-oak-slat-panel.html"
  },
  {
    "title": "Orb Spherical Knob",
    "category": "hardware",
    "style": "brushed-brass",
    "image": "/images/hardware-orb-knob-bb-large.jpg",
    "detailPage": "/material-detail-orb-spherical-knob.html"
  },
  {
    "title": "Vertical Garden Panel",
    "category": "panel",
    "style": "greenery",
    "image": "/images/panel-vertical-garden-large.jpg",
    "detailPage": "/material-detail-vertical-garden-panel.html"
  },
  {
    "title": "Vintage Floral Paper",
    "category": "wallpaper",
    "style": "floral",
    "image": "/images/wallpaper-vintage-floral-large.jpg",
    "detailPage": "/material-detail-vintage-floral-paper.html"
  },
  {
    "title": "Wall Panel",
    "category": "panel",
    "style": "other",
    "image": "/images/wall-panel.jpg",
    "detailPage": "/material-detail-wall-panel.html"
  }
]